kfutils/__init__.py
kfutils/cli.py
kfutils/funcs.py
kfutils-0.1.7.dist-info/LICENSE
kfutils-0.1.7.dist-info/METADATA
kfutils-0.1.7.dist-info/WHEEL
kfutils-0.1.7.dist-info/entry_points.txt
kfutils-0.1.7.dist-info/top_level.txt
kfutils-0.1.7.dist-info/zip-safe
kfutils-0.1.7.dist-info/RECORD
