Metadata-Version: 2.1
Name: kfutils
Version: 0.1.7
Summary: A tool for common data file operation.
Author: Koushik Naskar
Author-email: koushik.naskar9@gmail.com
License: MIT
Project-URL: Source Code, https://github.com/Koushikphy/kfutils
Keywords: File Operations
Classifier: Development Status :: 5 - Production/Stable
Classifier: Environment :: Console
Classifier: Intended Audience :: Science/Research
Classifier: Natural Language :: English
Classifier: License :: OSI Approved :: MIT License
Classifier: Operating System :: OS Independent
Classifier: Programming Language :: Python :: Implementation :: CPython
Classifier: Programming Language :: Python :: 3.6
Classifier: Topic :: System :: Shells
Requires-Python: >=3.6
License-File: LICENSE
Requires-Dist: csaps
Requires-Dist: tabulate
